loki_mcp_server/__init__.py
loki_mcp_server/__main__.py
loki_mcp_server/cli.py
loki_mcp_server/server.py
loki_mcp_server/tools/__init__.py
loki_mcp_server/tools/registry.py
loki_mcp_server/utils/__init__.py
loki_mcp_server/utils/client.py
loki_mcp_server/utils/helpers.py
loki_mcp_server/utils/logql.py
loki_mcp_server/utils/time.py
msrashed_loki_mcp_server-0.1.3.dist-info/METADATA
msrashed_loki_mcp_server-0.1.3.dist-info/WHEEL
msrashed_loki_mcp_server-0.1.3.dist-info/entry_points.txt
msrashed_loki_mcp_server-0.1.3.dist-info/RECORD
