Metadata-Version: 2.4
Name: msrashed-loki-mcp-server
Version: 0.1.3
Summary: Read-only Loki MCP server for log querying, searching, and analysis
Project-URL: Homepage, https://github.com/msalah-eg/loki-mcp-server
Project-URL: Repository, https://github.com/msalah-eg/loki-mcp-server
Project-URL: Issues, https://github.com/msalah-eg/loki-mcp-server/issues
Author-email: Mohamed Salah <mohamed@buyinggroup.com>
License: MIT
Keywords: ai,grafana,llm,logging,logs,loki,mcp,model-context-protocol,observability
Classifier: Development Status :: 4 - Beta
Classifier: Intended Audience :: Developers
Classifier: License :: OSI Approved :: MIT License
Classifier: Programming Language :: Python :: 3.12
Classifier: Programming Language :: Python :: 3.13
Classifier: Topic :: Software Development :: Libraries :: Python Modules
Classifier: Topic :: System :: Logging
Requires-Python: >=3.12
Requires-Dist: click>=8.1.0
Requires-Dist: fastmcp>=2.0.0
Requires-Dist: httpx>=0.27.0
Requires-Dist: mcp>=1.24.0
Requires-Dist: pydantic>=2.0.0
Requires-Dist: python-dateutil>=2.8.0
Provides-Extra: dev
Requires-Dist: pytest-asyncio>=0.24.0; extra == 'dev'
Requires-Dist: pytest>=8.0.0; extra == 'dev'
Requires-Dist: respx>=0.21.0; extra == 'dev'
Requires-Dist: ruff>=0.8.0; extra == 'dev'
